liturgical_colour/__init__.py
liturgical_colour/feasts.py
liturgical_colour/funcs.py
liturgical_colour/liturgical.py
liturgical_colour-0.3.0.dist-info/METADATA
liturgical_colour-0.3.0.dist-info/WHEEL
liturgical_colour-0.3.0.dist-info/entry_points.txt
liturgical_colour-0.3.0.dist-info/RECORD
