Metadata-Version: 2.1
Name: liturgical-colour
Version: 0.3.0
Summary: Library to determine liturgical dates and colours for the Anglican Church of England
Author: Jonathan Gazeley
Author-email: me@jonathangazeley.com
Requires-Python: >=3.11,<4.0
Classifier: Programming Language :: Python :: 3
Classifier: Programming Language :: Python :: 3.11
Classifier: Programming Language :: Python :: 3.12
Requires-Dist: python-dateutil (>=2.8.2,<3.0.0)
